fc_yu_chen_chen.py
ku_yu_chen-1.0.dist-info/METADATA
ku_yu_chen-1.0.dist-info/WHEEL
ku_yu_chen-1.0.dist-info/top_level.txt
ku_yu_chen-1.0.dist-info/RECORD
