Metadata-Version: 2.1
Name: ku-yu-chen
Version: 1.0
Summary: 使用方法：这个包只有一个变量name和age
Home-page: UNKNOWN
Author: 于晨晨
Author-email: 2790896061@qq.com
License: UNKNOWN
Platform: UNKNOWN
